pyfastutil/__init__.py
pyfastutil/__pyfastutil.so
pyfastutil/ints.py
pyfastutil/ints.pyi
pyfastutil/objects.py
pyfastutil/objects.pyi
pyfastutil/src/Compat.h
pyfastutil/src/PyFastUtil.h
pyfastutil/src/ints/BigIntArrayList.h
pyfastutil/src/ints/BigIntArrayListIter.h
pyfastutil/src/ints/IntArrayList.h
pyfastutil/src/ints/IntArrayListIter.h
pyfastutil/src/ints/IntIntHashMap.h
pyfastutil/src/ints/IntLinkedList.h
pyfastutil/src/ints/IntLinkedListIter.h
pyfastutil/src/objects/ObjectArrayList.h
pyfastutil/src/objects/ObjectArrayListIter.h
pyfastutil/src/objects/ObjectLinkedList.h
pyfastutil/src/objects/ObjectLinkedListIter.h
pyfastutil/src/unsafe/ASM.h
pyfastutil/src/unsafe/SIMD.h
pyfastutil/src/unsafe/SIMDLowAVX512.h
pyfastutil/src/unsafe/Unsafe.h
pyfastutil/src/utils/PythonPCH.h
pyfastutil/src/utils/PythonUtils.h
pyfastutil/src/utils/Utils.h
pyfastutil/src/utils/include/CPythonSort.h
pyfastutil/src/utils/include/TimSort.h
pyfastutil/src/utils/include/UnorderedDense.h
pyfastutil/src/utils/memory/AlignedAllocator.h
pyfastutil/src/utils/memory/FastMemcpy.h
pyfastutil/src/utils/memory/PreFetch.h
pyfastutil/src/utils/simd/BitonicSort.h
pyfastutil/src/utils/simd/SIMDHelper.h
pyfastutil/src/utils/simd/SIMDUtils.h
pyfastutil/src/utils/thread/ScheduledThreadPool.h
pyfastutil/unsafe/ASM.pyi
pyfastutil/unsafe/SIMD.pyi
pyfastutil/unsafe/SIMDLowAVX512.pyi
pyfastutil/unsafe/Unsafe.pyi
pyfastutil/unsafe/__SIMDLowAVX512Defines.py
pyfastutil/unsafe/__SIMDLowAVX512Defines.pyi
pyfastutil/unsafe/__init__.py
pyfastutil/unsafe/__init__.pyi
PyFastUtil-0.1.1.dist-info/LICENSE
PyFastUtil-0.1.1.dist-info/METADATA
PyFastUtil-0.1.1.dist-info/WHEEL
PyFastUtil-0.1.1.dist-info/top_level.txt
PyFastUtil-0.1.1.dist-info/RECORD
