Metadata-Version: 2.1
Name: PyFastUtil
Version: 0.1.1
Summary: PyFastUtil provides fast, fully Python-compatible data structures along with bindings to low-level interfaces.
Author-email: xia__mc <xiayichun0512@gmail.com>
Project-URL: Homepage, https://github.com/xia-mc/PyFastUtil
Project-URL: Issues, https://github.com/xia-mc/PyFastUtil/issues
Classifier: Programming Language :: Python :: 3
Classifier: License :: OSI Approved :: Apache Software License
Classifier: Operating System :: OS Independent
Requires-Python: >=3.9
License-File: LICENSE
